prettyplease/__init__.py
prettyplease/prettyplease.py
prettyplease-0.13.1.dist-info/licenses/LICENSE
prettyplease-0.13.1.dist-info/METADATA
prettyplease-0.13.1.dist-info/WHEEL
prettyplease-0.13.1.dist-info/top_level.txt
prettyplease-0.13.1.dist-info/RECORD
