Metadata-Version: 2.4
Name: prettyplease
Version: 0.13.1
Summary: Create pretty corner plots.
Home-page: https://github.com/svisak/prettyplease
Author: Isak Svensson
Author-email: isak.svensson@tu-darmstadt.de
Project-URL: Bug Tracker, https://github.com/svisak/prettyplease/issues
Classifier: Programming Language :: Python :: 3
Classifier: License :: OSI Approved :: GNU General Public License (GPL)
Classifier: Operating System :: OS Independent
Requires-Python: >=3.6
License-File: LICENSE
Requires-Dist: numpy
Requires-Dist: matplotlib
Dynamic: license-file
